{
  "branch": "E2.5",
  "claim_boundary": {
    "adapter_required_for_d2_3_semantics": true,
    "adapter_triggered_runtime_compatible": true,
    "core_task_requested": false,
    "movement_claim_allowed": false,
    "native_d2_3_equivalent_autonomy": false,
    "native_grc9v3_evidence": false,
    "native_lgrc9v3_execution": true,
    "native_packet_execution": true,
    "native_static_route_autonomy": true
  },
  "command": ".venv/bin/python experiments/2026-05-N03-grc9v3-polarized-basin-loops/scripts/build_e2_5_runtime_closeout.py",
  "errors": [],
  "evidence_chain": [
    {
      "artifact": "outputs/e2_0_runtime_feasibility.json",
      "branch": "E2.0",
      "classification": "single scheduled packet feasibility",
      "status": "passed"
    },
    {
      "artifact": "outputs/e2_1_scheduled_packet_route_replay.json",
      "branch": "E2.1",
      "classification": "scheduled native packet route replay",
      "status": "passed"
    },
    {
      "artifact": "outputs/e2_2_runtime_ledger_extraction.json",
      "branch": "E2.2",
      "classification": "runtime ledger extraction and ledger-only validation",
      "status": "passed"
    },
    {
      "artifact": "outputs/e2_3_adapter_triggered_runtime_loop.json",
      "branch": "E2.3",
      "classification": "adapter_triggered_runtime_loop_with_controls",
      "status": "passed"
    },
    {
      "artifact": "outputs/e2_3a_adapter_triggered_runtime_loop_hardening.json",
      "branch": "E2.3-A",
      "classification": "adapter-triggered runtime hardening passed",
      "status": "passed"
    },
    {
      "artifact": "outputs/e2_4_native_autonomy_feasibility.json",
      "branch": "E2.4",
      "classification": "native_static_route_autonomy_feasible_d2_3_surplus_trigger_missing",
      "status": "passed"
    },
    {
      "artifact": "outputs/e2_4a_native_autonomy_boundary.json",
      "branch": "E2.4-A",
      "classification": "native autonomy boundary validation passed",
      "status": "passed"
    }
  ],
  "final_conclusions": [
    "Existing LGRC9V3 can execute scheduled packet departure/arrival events.",
    "Existing LGRC9V3 can replay the declared D2.3 packet route when packets are scheduled.",
    "E2.3 demonstrates a D2.3-aligned adapter-triggered runtime loop with controls preserved.",
    "E2.2 extracts replayable E1-compatible ledgers from E2.3 runtime evidence.",
    "Existing LGRC9V3 native static-route autonomy exists through causal flux routes and autonomous producers.",
    "Existing native autonomy is not D2.3-equivalent because pole-mask route semantics, source-pole surplus threshold trigger, and D2.3 self-rearm labels remain adapter-derived.",
    "No movement, locomotion, agency, biological, or native GRC9V3 loop claim is made.",
    "No `src/*` change or core task is requested by this experiment closeout."
  ],
  "next_branch_decision": "Close E2. Future work may either publish N03 with this bounded runtime classification, or open a separate core-design task for a native pole-surplus trigger primitive. That core task is not requested by this experiment closeout.",
  "schema": "n03_e2_5_lgrc9v3_runtime_closeout_v1",
  "selected_classifications": [
    "native_packet_execution_compatible",
    "adapter_triggered_runtime_compatible",
    "native_static_route_autonomy_available",
    "missing_native_surplus_trigger_primitive"
  ],
  "status": "passed"
}
